livekit_nextevi/__init__.py
livekit_nextevi/nextevi_stt.py
livekit_nextevi/version.py
livekit_nextevi/realtime/__init__.py
livekit_nextevi/realtime/auth.py
livekit_nextevi/realtime/config.py
livekit_nextevi/realtime/nextevi_realtime_model.py
livekit_nextevi/realtime/nextevi_websocket_client.py
livekit_plugins_nextevi-0.1.0.dist-info/METADATA
livekit_plugins_nextevi-0.1.0.dist-info/WHEEL
livekit_plugins_nextevi-0.1.0.dist-info/entry_points.txt
livekit_plugins_nextevi-0.1.0.dist-info/RECORD
