Metadata-Version: 2.4
Name: livekit-plugins-nextevi
Version: 0.1.0
Summary: LiveKit Agents plugin for NextEVI voice AI platform with real-time speech-to-speech capabilities
Project-URL: Documentation, https://docs.nextevi.com
Project-URL: Website, https://nextevi.com
Project-URL: Source, https://github.com/nextevi/livekit-nextevi
Project-URL: Issues, https://github.com/nextevi/livekit-nextevi/issues
Author-email: NextEVI <team@nextevi.com>
License: Apache-2.0
Keywords: audio,livekit,nextevi,realtime,video,voice-ai,webrtc
Classifier: Intended Audience :: Developers
Classifier: License :: OSI Approved :: Apache Software License
Classifier: Programming Language :: Python :: 3
Classifier: Programming Language :: Python :: 3 :: Only
Classifier: Programming Language :: Python :: 3.9
Classifier: Programming Language :: Python :: 3.10
Classifier: Topic :: Multimedia :: Sound/Audio
Classifier: Topic :: Multimedia :: Video
Classifier: Topic :: Scientific/Engineering :: Artificial Intelligence
Requires-Python: >=3.9.0
Requires-Dist: aiohttp>=3.8.0
Requires-Dist: livekit-agents[codecs,images]>=1.2.8
Requires-Dist: pydantic>=2.0.0
Requires-Dist: websockets>=12.0
